Verilog/akh/FourBitCounter.v
// An active low reset signal is used for resetting the counter.
module counter (input clk, input rstn, output reg[3:0] out);
    always @ (posedge clk) begin
    if (! rstn)
        out <= 0;
    else 
        out <= out + 1;
    end
endmodule

module tb_counter;
    reg clk;
    reg rstn;
    wire [3:0] out;
 
    counter c0(.clk(clk), .rstn (rstn), .out (out));

// Generate a clock that should be driven to design
// This clock will flip its value every 5ns -> time period = 10ns -> freq = 100 MHz
    always #5 clk = ~clk;

    initial
    begin
    $dumpfile("FourBitCounter.vcd");
    $dumpvars(0,tb_counter);

    $display("Clock \t Reset \t Output");
    $monitor("%b %b %b", clk, rstn, out);

        clk <= 0;
        rstn <= 0;
 
        #20   rstn <= 1;
        #250   rstn <= 0;
        #50   rstn <= 1;
        #20
    $finish;
    end
endmodule

Verilog/akh/FourBitCounter.vcd
$date
	Wed Jul 06 21:10:27 2022
$end
$version
	Icarus Verilog
$end
$timescale
	1s
$end
$scope module tb_counter $end
$var wire 4 ! out [3:0] $end
$var reg 1 " clk $end
$var reg 1 # rstn $end
$scope module c0 $end
$var wire 1 " clk $end
$var wire 1 # rstn $end
$var reg 4 $ out [3:0] $end
$upscope $end
$upscope $end
$enddefinitions $end
#0
$dumpvars
bx $
0#
0"
bx !
$end
#5
b0 !
b0 $
1"
#10
0"
#15
1"
#20
1#
0"
#25
b1 !
b1 $
1"
#30
0"
#35
b10 !
b10 $
1"
#40
0"
#45
b11 !
b11 $
1"
#50
0"
#55
b100 !
b100 $
1"
#60
0"
#65
b101 !
b101 $
1"
#70
0"
#75
b110 !
b110 $
1"
#80
0"
#85
b111 !
b111 $
1"
#90
0"
#95
b1000 !
b1000 $
1"
#100
0"
#105
b1001 !
b1001 $
1"
#110
0"
#115
b1010 !
b1010 $
1"
#120
0"
#125
b1011 !
b1011 $
1"
#130
0"
#135
b1100 !
b1100 $
1"
#140
0"
#145
b1101 !
b1101 $
1"
#150
0"
#155
b1110 !
b1110 $
1"
#160
0"
#165
b1111 !
b1111 $
1"
#170
0"
#175
b0 !
b0 $
1"
#180
0"
#185
b1 !
b1 $
1"
#190
0"
#195
b10 !
b10 $
1"
#200
0"
#205
b11 !
b11 $
1"
#210
0"
#215
b100 !
b100 $
1"
#220
0"
#225
b101 !
b101 $
1"
#230
0"
#235
b110 !
b110 $
1"
#240
0"
#245
b111 !
b111 $
1"
#250
0"
#255
b1000 !
b1000 $
1"
#260
0"
#265
b1001 !
b1001 $
1"
#270
0#
0"
#275
b0 !
b0 $
1"
#280
0"
#285
1"
#290
0"
#295
1"
#300
0"
#305
1"
#310
0"
#315
1"
#320
1#
0"
#325
b1 !
b1 $
1"
#330
0"
#335
b10 !
b10 $
1"
